layercode_create_app/__init__.py
layercode_create_app/agents/__init__.py
layercode_create_app/agents/bakery.py
layercode_create_app/agents/base.py
layercode_create_app/agents/echo.py
layercode_create_app/agents/outdoor_shop.py
layercode_create_app/agents/prompts/bakery.txt
layercode_create_app/agents/prompts/outdoor_shop.txt
layercode_create_app/agents/prompts/starter.txt
layercode_create_app/agents/slow_agent.py
layercode_create_app/agents/starter.py
layercode_create_app/cli.py
layercode_create_app/config.py
layercode_create_app/logging.py
layercode_create_app/py.typed
layercode_create_app/sdk/__init__.py
layercode_create_app/sdk/auth.py
layercode_create_app/sdk/events.py
layercode_create_app/sdk/stream.py
layercode_create_app/server/__init__.py
layercode_create_app/server/app.py
layercode_create_app/server/conversation.py
layercode_create_app/tunnel.py
layercode_create_app-0.2.0.dist-info/WHEEL
layercode_create_app-0.2.0.dist-info/entry_points.txt
layercode_create_app-0.2.0.dist-info/METADATA
layercode_create_app-0.2.0.dist-info/RECORD
