Metadata-Version: 2.4
Name: layercode-create-app
Version: 0.2.0
Summary: Fast scaffolding for LayerCode-ready FastAPI backends
Author: Jan Siml
Author-email: Jan Siml <49557684+svilupp@users.noreply.github.com>
License-Expression: MIT
Requires-Dist: fastapi>=0.115.0
Requires-Dist: httpx>=0.27.2
Requires-Dist: logfire[fastapi]>=4.14.2
Requires-Dist: loguru>=0.7.3
Requires-Dist: pydantic>=2.9.2
Requires-Dist: pydantic-ai>=1.9.1
Requires-Dist: pydantic-settings>=2.11.0
Requires-Dist: python-dotenv>=1.0.1
Requires-Dist: textprompts>=1.1.0
Requires-Dist: uvicorn[standard]>=0.31.1
Requires-Dist: ty>=0.0.8 ; extra == 'dev'
Requires-Dist: pytest>=8.3.2 ; extra == 'dev'
Requires-Dist: pytest-asyncio>=0.24.0 ; extra == 'dev'
Requires-Dist: ruff>=0.6.8 ; extra == 'dev'
Requires-Python: >=3.12
Provides-Extra: dev
